somnopy/HumeDataLoader.py
somnopy/RemLogicDataLoader.py
somnopy/__init__.py
somnopy/event_detection.py
somnopy/metrics.py
somnopy/polysomnography.py
somnopy/somno.py
somnopy/utils.py
somnopy/tests/test_somnopy.py
somnopy-0.0.10.dist-info/licenses/LICENSE
somnopy-0.0.10.dist-info/METADATA
somnopy-0.0.10.dist-info/WHEEL
somnopy-0.0.10.dist-info/top_level.txt
somnopy-0.0.10.dist-info/RECORD
