Metadata-Version: 2.4
Name: somnopy
Version: 0.0.10
Summary: PSG Power for Python
Author-email: Thea Ng <somneurolab@umass.edu>, Roger Balcells Sanchez <somneurolab@umass.edu>, Atif Abedeen <somneurolab@umass.edu>, Lindsey Mooney <somneurolab@umass.edu>
Project-URL: Homepage, https://github.com/Somneuro-Lab-UMass/PSG-Party
Project-URL: Issues, https://github.com/Somneuro-Lab-UMass/PSG-Party/issues
Classifier: Programming Language :: Python :: 3
Classifier: Operating System :: OS Independent
Requires-Python: >=3.8
License-File: LICENSE
Provides-Extra: docs
Requires-Dist: sphinx>=4.0; extra == "docs"
Requires-Dist: sphinx-rtd-theme; extra == "docs"
Requires-Dist: setuptools>=61.0; extra == "docs"
Requires-Dist: numpy>=1.23.5; extra == "docs"
Requires-Dist: pandas>=1.5.2; extra == "docs"
Requires-Dist: mne>=1.8.0; extra == "docs"
Requires-Dist: matplotlib>=3.6.2; extra == "docs"
Requires-Dist: pytz>=2022.6; extra == "docs"
Requires-Dist: scipy>=1.9.3; extra == "docs"
Requires-Dist: seaborn>=0.12.1; extra == "docs"
Requires-Dist: statsmodels>=0.13.5; extra == "docs"
Dynamic: license-file
